codehub/__init__.py
codehub/api.py
codehub/pkg_info.py
codehub/clitools/__init__.py
codehub/clitools/cli.py
codehub/clitools/codefire.py
codehub/clitools/utils/FileUtil.py
codehub/clitools/utils/StringUtil.py
codehub/clitools/utils/__init__.py
codehub/utils/__init__.py
codehub/utils/pathutils.py
codehub-0.0.4.6.dist-info/LICENSE
codehub-0.0.4.6.dist-info/METADATA
codehub-0.0.4.6.dist-info/WHEEL
codehub-0.0.4.6.dist-info/entry_points.txt
codehub-0.0.4.6.dist-info/top_level.txt
codehub-0.0.4.6.dist-info/RECORD
